[{"target":42,"price":42.140,"returns":0,"ticker":"GTT","note":"GTT Communications Inc (GTT) Receives $42.14 Average Price Target from Analysts - Finance Daily","to_char":"04/30/2019","q_eps":null,"a_eps":-4.800,"report":"analyst","q_pe":null,"a_pe":null,"divyield":null},{"target":22,"price":21.810,"returns":1,"ticker":"BLX","note":"Banco Latinoamericano de Comerci Extr SA (BLX) Receives $22.00 Consensus Target Price from Analysts - Rockland Register","to_char":"04/28/2019","q_eps":null,"a_eps":0.450,"report":"analyst","q_pe":null,"a_pe":null,"divyield":0.071},{"target":89,"price":86.970,"returns":2,"ticker":"FSV","note":"BMO Capital Markets Reiterates C$89.00 Price Target for FirstService (FSV) - Rockland Register","to_char":"04/29/2019","q_eps":null,"a_eps":1.690,"report":"analyst","q_pe":null,"a_pe":null,"divyield":0.006},{"target":26,"price":25.280,"returns":2,"ticker":"RST","note":"Rosetta Stone Inc (RST) Receives $25.75 Average Target Price from Brokerages - Mayfield Recorder","to_char":"04/27/2019","q_eps":null,"a_eps":-0.950,"report":"analyst","q_pe":null,"a_pe":null,"divyield":null},{"target":45,"price":43.370,"returns":3,"ticker":"BMRC","note":"Bank of Marin Bancorp (BMRC) Receives $44.75 Consensus Price Target from Analysts - Tech Know Bits","to_char":"04/30/2019","q_eps":null,"a_eps":2.410,"report":"analyst","q_pe":null,"a_pe":null,"divyield":0.016}]
