[{"target":62,"price":65.540,"returns":-6,"ticker":"NWE","note":"NorthWestern Corp (NWE) Receives $61.50 Consensus Price Target from Analysts - Fairfield Current","to_char":"02/17/2019","q_eps":null,"a_eps":3.920,"report":"analyst","q_pe":null,"a_pe":null,"divyield":null},{"target":95,"price":99.720,"returns":-5,"ticker":"EXR","note":"Extra Space Storage, Inc. (EXR) Received $95.00 Average Target Price from Analysts - BharataPress","to_char":"02/17/2019","q_eps":null,"a_eps":4.160,"report":"analyst","q_pe":null,"a_pe":null,"divyield":null},{"target":80,"price":78.020,"returns":3,"ticker":"CHCO","note":"City Holding (CHCO) Receives $80.00 Consensus Price Target from Analysts - PressOracle","to_char":"02/17/2019","q_eps":null,"a_eps":4.490,"report":"analyst","q_pe":null,"a_pe":null,"divyield":null},{"target":108,"price":102.690,"returns":5,"ticker":"CFR","note":"Cullen/Frost Bankers, Inc. (CFR) Received $108.63 Average Target Price from Brokerages - BharataPress","to_char":"02/17/2019","q_eps":null,"a_eps":6.910,"report":"analyst","q_pe":null,"a_pe":null,"divyield":null},{"target":30,"price":26.200,"returns":13,"ticker":"CAI","note":"CAI International Inc (CAI) Receives $29.50 Average Price Target from Brokerages - Fairfield Current","to_char":"02/17/2019","q_eps":null,"a_eps":4.630,"report":"analyst","q_pe":null,"a_pe":null,"divyield":null}]
