[{"Ticker": "stl", "Stock": "Sterling Bancorp", "Type": "Q", "Dividend": "0.07", "LastPrice": "21.66", "Yield": "1.29%", "ExDay": "5/3", "PayDay": "5/20"}, {"Ticker": "lsbk", "Stock": "Lake Shore Bancorp Inc", "Type": "Q", "Dividend": "0.12", "LastPrice": "14.95", "Yield": "3.21%", "ExDay": "5/3", "PayDay": "5/20"}, {"Ticker": "amp", "Stock": "Ameriprise Financial Inc", "Type": "Q", "Dividend": "0.97", "LastPrice": "147.37", "Yield": "2.63%", "ExDay": "5/3", "PayDay": "5/17"}, {"Ticker": "fbiz", "Stock": "First Business Financial Services Inc", "Type": "Q", "Dividend": "0.15", "LastPrice": "23.13", "Yield": "2.59%", "ExDay": "5/3", "PayDay": "5/16"}, {"Ticker": "ab", "Stock": "Alliancebernstein Holding L.P. Units", "Type": "Q", "Dividend": "0.49", "LastPrice": "29.50", "Yield": "6.64%", "ExDay": "5/3", "PayDay": "5/16"}, {"Ticker": "alx", "Stock": "Alexanders Inc", "Type": "Q", "Dividend": "4.5", "LastPrice": "387.87", "Yield": "4.64%", "ExDay": "5/3", "PayDay": "5/17"}, {"Ticker": "asrv", "Stock": "Ameriserv Financial Inc", "Type": "Q", "Dividend": "0.025", "LastPrice": "4.20", "Yield": "2.38%", "ExDay": "5/3", "PayDay": "5/20"}, {"Ticker": "lyts", "Stock": "Lsi Industries Inc", "Type": "Q", "Dividend": "0.05", "LastPrice": "3.48", "Yield": "5.75%", "ExDay": "5/3", "PayDay": "5/14"}, {"Ticker": "pub", "Stock": "Peoples Utah Bancorp", "Type": "Q", "Dividend": "0.12", "LastPrice": "28.37", "Yield": "1.69%", "ExDay": "5/3", "PayDay": "5/13"}, {"Ticker": "dit", "Stock": "Amcon Distributing Company", "Type": "Q", "Dividend": "0.18", "LastPrice": "93.29", "Yield": "0.77%", "ExDay": "5/3", "PayDay": "5/28"}, {"Ticker": "ibtx", "Stock": "Independent Bank Group Inc", "Type": "Q", "Dividend": "0.25", "LastPrice": "56.18", "Yield": "1.78%", "ExDay": "5/3", "PayDay": "5/16"}, {"Ticker": "sjw", "Stock": "Sjw Group (de", "Type": "Q", "Dividend": "0.3", "LastPrice": "60.46", "Yield": "1.98%", "ExDay": "5/3", "PayDay": "6/3"}, {"Ticker": "matw", "Stock": "Matthews International Corporation - Class A Commo", "Type": "Q", "Dividend": "0.2", "LastPrice": "37.44", "Yield": "2.14%", "ExDay": "5/3", "PayDay": "5/20"}, {"Ticker": "uan", "Stock": "Cvr Partners Lpunits Representing Limited", "Type": "Q", "Dividend": "0.07", "LastPrice": "3.59", "Yield": "7.80%", "ExDay": "5/3", "PayDay": "5/13"}, {"Ticker": "laz", "Stock": "Lazard LTD. Lazard LTD. Class A", "Type": "Q", "Dividend": "0.47", "LastPrice": "38.18", "Yield": "4.92%", "ExDay": "5/3", "PayDay": "5/17"}, {"Ticker": "srce", "Stock": "1st Source Corporation", "Type": "Q", "Dividend": "0.27", "LastPrice": "47.51", "Yield": "2.27%", "ExDay": "5/3", "PayDay": "5/15"}, {"Ticker": "stnd", "Stock": "Standard Avb Financial Corp", "Type": "Q", "Dividend": "0.221", "LastPrice": "27.49", "Yield": "3.22%", "ExDay": "5/3", "PayDay": "5/20"}, {"Ticker": "glop", "Stock": "Gaslog Partners Lpunits Representing Limit", "Type": "Q", "Dividend": "0.55", "LastPrice": "21.10", "Yield": "10.43%", "ExDay": "5/3", "PayDay": "5/10"}, {"Ticker": "ocfc", "Stock": "Oceanfirst Financial Corp", "Type": "Q", "Dividend": "0.17", "LastPrice": "25.18", "Yield": "2.70%", "ExDay": "5/3", "PayDay": "5/17"}, {"Ticker": "bbdo", "Stock": "Banco Bradesco SA American Depositary Shares (each", "Type": "M", "Dividend": "0.0045", "LastPrice": "7.89", "Yield": "0.69%", "ExDay": "5/3", "PayDay": "6/10"}, {"Ticker": "wmk", "Stock": "Weis Markets Inc", "Type": "Q", "Dividend": "0.31", "LastPrice": "42.05", "Yield": "2.95%", "ExDay": "5/3", "PayDay": "5/20"}, {"Ticker": "sifi", "Stock": "SI Financial Group Inc", "Type": "Q", "Dividend": "0.06", "LastPrice": "14.30", "Yield": "1.68%", "ExDay": "5/3", "PayDay": "5/16"}, {"Ticker": "bgsf", "Stock": "BG Staffing Inc", "Type": "Q", "Dividend": "0.3", "LastPrice": "22.75", "Yield": "5.27%", "ExDay": "5/3", "PayDay": "5/13"}, {"Ticker": "fmx", "Stock": "Fomento Economico Mexicano S.A.B. DE C.V.", "Type": "S", "Dividend": "0.77", "LastPrice": "99.03", "Yield": "0.78%", "ExDay": "5/3", "PayDay": "5/17"}, {"Ticker": "kof", "Stock": "Coca Cola Femsa S.A.B. DE C.V. American Depositar", "Type": "S", "Dividend": "0.77", "LastPrice": "64.64", "Yield": "1.19%", "ExDay": "5/3", "PayDay": "5/17"}, {"Ticker": "mpv", "Stock": "Barings Participation Investors", "Type": "Q", "Dividend": "0.27", "LastPrice": "15.50", "Yield": "6.97%", "ExDay": "5/3", "PayDay": "5/17"}, {"Ticker": "ulh", "Stock": "Universal Logistics Holdings Inc", "Type": "Q", "Dividend": "0.105", "LastPrice": "23.26", "Yield": "1.81%", "ExDay": "5/3", "PayDay": "5/16"}, {"Ticker": "dlng.pra", "Stock": "Dynagas Lng Partners LP 9.00% Series A Cumulative", "Type": "Q", "Dividend": "0.5625", "LastPrice": "20.80", "Yield": "10.82%", "ExDay": "5/3", "PayDay": "5/13"}, {"Ticker": "hbcp", "Stock": "Home Bancorp Inc", "Type": "Q", "Dividend": "0.21", "LastPrice": "36.21", "Yield": "2.32%", "ExDay": "5/3", "PayDay": "5/17"}, {"Ticker": "ntb", "Stock": "Bank of N.T. Butterfield & Son Limited (the) Votin", "Type": "Q", "Dividend": "0.44", "LastPrice": "40.26", "Yield": "4.37%", "ExDay": "5/3", "PayDay": "5/17"}, {"Ticker": "cs", "Stock": "Credit Suisse Group American Depositary Shares", "Type": "A", "Dividend": "0.2641", "LastPrice": "13.24", "Yield": "1.99%", "ExDay": "5/3", "PayDay": "5/17"}, {"Ticker": "nblx", "Stock": "Noble Midstream Partners Lpunits Represent", "Type": "Q", "Dividend": "0.6132", "LastPrice": "33.90", "Yield": "7.24%", "ExDay": "5/3", "PayDay": "5/13"}, {"Ticker": "hcp", "Stock": "Hcp Inc", "Type": "Q", "Dividend": "0.37", "LastPrice": "30.54", "Yield": "4.85%", "ExDay": "5/3", "PayDay": "5/21"}, {"Ticker": "tts", "Stock": "Tile Shop Hldgs Inc", "Type": "Q", "Dividend": "0.05", "LastPrice": "4.72", "Yield": "4.24%", "ExDay": "5/3", "PayDay": "5/17"}, {"Ticker": "gne.pra", "Stock": "Genie Energy LTD. Series 2012 - A Preferred Stock", "Type": "Q", "Dividend": "0.1594", "LastPrice": "8.24", "Yield": "7.74%", "ExDay": "5/3", "PayDay": "5/15"}, {"Ticker": "cvi", "Stock": "Cvr Energy Inc", "Type": "Q", "Dividend": "0.75", "LastPrice": "44.63", "Yield": "6.72%", "ExDay": "5/3", "PayDay": "5/13"}, {"Ticker": "nsec", "Stock": "National Security Group Inc", "Type": "Q", "Dividend": "0.05", "LastPrice": "11.42", "Yield": "1.75%", "ExDay": "5/3", "PayDay": "5/31"}, {"Ticker": "nbl", "Stock": "Noble Energy Inc", "Type": "Q", "Dividend": "0.12", "LastPrice": "25.48", "Yield": "1.88%", "ExDay": "5/3", "PayDay": "5/20"}, {"Ticker": "c", "Stock": "Citigroup Inc", "Type": "Q", "Dividend": "0.45", "LastPrice": "70.36", "Yield": "2.56%", "ExDay": "5/3", "PayDay": "5/24"}, {"Ticker": "wabc", "Stock": "Westamerica Bancorporation", "Type": "Q", "Dividend": "0.41", "LastPrice": "63.98", "Yield": "2.56%", "ExDay": "5/3", "PayDay": "5/17"}, {"Ticker": "vno", "Stock": "Vornado Realty Trust", "Type": "Q", "Dividend": "0.66", "LastPrice": "67.96", "Yield": "3.88%", "ExDay": "5/3", "PayDay": "5/17"}, {"Ticker": "capl", "Stock": "Crossamerica Partners Lpunits Representing", "Type": "Q", "Dividend": "0.525", "LastPrice": "18.17", "Yield": "11.56%", "ExDay": "5/3", "PayDay": "5/13"}, {"Ticker": "ltxb", "Stock": "Legacytexas Financial Group Inc", "Type": "Q", "Dividend": "0.25", "LastPrice": "39.99", "Yield": "2.50%", "ExDay": "5/3", "PayDay": "5/20"}, {"Ticker": "shlx", "Stock": "Shell Midstream Partners L.P.UNITS Repres", "Type": "Q", "Dividend": "0.415", "LastPrice": "20.06", "Yield": "8.28%", "ExDay": "5/3", "PayDay": "5/15"}, {"Ticker": "mci", "Stock": "Barings Corporate Investors", "Type": "Q", "Dividend": "0.3", "LastPrice": "15.99", "Yield": "7.50%", "ExDay": "5/3", "PayDay": "5/17"}, {"Ticker": "pebo", "Stock": "Peoples Bancorp Inc", "Type": "Q", "Dividend": "0.34", "LastPrice": "32.56", "Yield": "4.18%", "ExDay": "5/3", "PayDay": "5/20"}, {"Ticker": "syf", "Stock": "Synchrony Financial", "Type": "Q", "Dividend": "0.21", "LastPrice": "34.15", "Yield": "2.46%", "ExDay": "5/3", "PayDay": "5/16"}, {"Ticker": "wbs", "Stock": "Webster Financial Corporation", "Type": "Q", "Dividend": "0.4", "LastPrice": "53.07", "Yield": "3.01%", "ExDay": "5/3", "PayDay": "5/20"}, {"Ticker": "cnxm", "Stock": "Cnx Midstream Partners Lpunits Representin", "Type": "Q", "Dividend": "0.3732", "LastPrice": "15.30", "Yield": "9.76%", "ExDay": "5/3", "PayDay": "5/14"}, {"Ticker": "ida", "Stock": "Idacorp Inc", "Type": "Q", "Dividend": "0.63", "LastPrice": "98.37", "Yield": "2.56%", "ExDay": "5/3", "PayDay": "5/30"}, {"Ticker": "bbd", "Stock": "Banco Bradesco SA American Depositary Shares", "Type": "M", "Dividend": "0.0050", "LastPrice": "8.98", "Yield": "0.66%", "ExDay": "5/3", "PayDay": "6/10"}, {"Ticker": "teo", "Stock": "Telecom Argentina SA", "Type": "A", "Dividend": "0.4504", "LastPrice": "13.43", "Yield": "3.35%", "ExDay": "5/3", "PayDay": "5/14"}, {"Ticker": "evtc", "Stock": "Evertec Inc", "Type": "Q", "Dividend": "0.05", "LastPrice": "29.71", "Yield": "0.67%", "ExDay": "5/3", "PayDay": "6/7"}, {"Ticker": "hafc", "Stock": "Hanmi Financial Corporation", "Type": "Q", "Dividend": "0.24", "LastPrice": "23.73", "Yield": "4.05%", "ExDay": "5/3", "PayDay": "5/31"}, {"Ticker": "ibcp", "Stock": "Independent Bank Corporation", "Type": "Q", "Dividend": "0.18", "LastPrice": "21.55", "Yield": "3.34%", "ExDay": "5/3", "PayDay": "5/15"}, {"Ticker": "txn", "Stock": "Texas Instruments Incorporated", "Type": "Q", "Dividend": "0.77", "LastPrice": "117.46", "Yield": "2.62%", "ExDay": "5/3", "PayDay": "5/20"}, {"Ticker": "cwt", "Stock": "California Water Service Group", "Type": "Q", "Dividend": "0.1975", "LastPrice": "49.72", "Yield": "1.59%", "ExDay": "5/3", "PayDay": "5/17"}, {"Ticker": "krp", "Stock": "Kimbell Royalty Partnersunits Representing", "Type": "Q", "Dividend": "0.37", "LastPrice": "16.61", "Yield": "8.91%", "ExDay": "5/3", "PayDay": "5/13"}, {"Ticker": "oak", "Stock": "Oaktree Capital Group Llc Class A Units Represent", "Type": "Q", "Dividend": "1.05", "LastPrice": "50.31", "Yield": "8.35%", "ExDay": "5/3", "PayDay": "5/10"}, {"Ticker": "royt", "Stock": "Pacific Coast Oil Trust Units of Beneficial Intere", "Type": "M", "Dividend": "0.0279", "LastPrice": "2.26", "Yield": "14.82%", "ExDay": "5/3", "PayDay": "5/20"}, {"Ticker": "gmlp", "Stock": "Golar Lng Partners Lpunits Representing", "Type": "Q", "Dividend": "0.4042", "LastPrice": "12.90", "Yield": "12.53%", "ExDay": "5/6", "PayDay": "5/14"}, {"Ticker": "cig", "Stock": "Comp EN DE MN Cemig Ads American Depositary Shares", "Type": "A", "Dividend": "0.1142", "LastPrice": "3.68", "Yield": "3.10%", "ExDay": "5/6", "PayDay": "NA"}, {"Ticker": "safm", "Stock": "Sanderson Farms Inc", "Type": "Q", "Dividend": "0.32", "LastPrice": "147.94", "Yield": "0.87%", "ExDay": "5/6", "PayDay": "5/21"}, {"Ticker": "sun", "Stock": "Sunoco Lpunits Representing Limited Partne", "Type": "Q", "Dividend": "0.8255", "LastPrice": "31.18", "Yield": "10.59%", "ExDay": "5/6", "PayDay": "5/15"}, {"Ticker": "fe", "Stock": "Firstenergy Corp", "Type": "Q", "Dividend": "0.38", "LastPrice": "41.97", "Yield": "3.62%", "ExDay": "5/6", "PayDay": "6/1"}, {"Ticker": "tgp", "Stock": "Teekay Lng Partners L.P.", "Type": "Q", "Dividend": "0.19", "LastPrice": "14.89", "Yield": "5.10%", "ExDay": "5/6", "PayDay": "5/15"}, {"Ticker": "ccr", "Stock": "Consol Coal Resources Lpunits Representing", "Type": "Q", "Dividend": "0.5125", "LastPrice": "17.72", "Yield": "11.57%", "ExDay": "5/6", "PayDay": "5/15"}, {"Ticker": "ngl", "Stock": "Ngl Energy Partners Lpunits Representing L", "Type": "Q", "Dividend": "0.39", "LastPrice": "13.52", "Yield": "11.54%", "ExDay": "5/6", "PayDay": "5/15"}, {"Ticker": "usdp", "Stock": "Usd Partners Lpunits Representing Limited", "Type": "Q", "Dividend": "0.3625", "LastPrice": "11.14", "Yield": "13.02%", "ExDay": "5/6", "PayDay": "5/15"}, {"Ticker": "sph", "Stock": "Suburban Propane Partners L.P.", "Type": "Q", "Dividend": "0.6", "LastPrice": "23.48", "Yield": "10.22%", "ExDay": "5/6", "PayDay": "5/14"}, {"Ticker": "intc", "Stock": "Intel Corporation", "Type": "Q", "Dividend": "0.315", "LastPrice": "50.55", "Yield": "2.49%", "ExDay": "5/6", "PayDay": "6/1"}, {"Ticker": "cig.c", "Stock": "Comp EN DE MN Cemig Ads American Depositary Receip", "Type": "A", "Dividend": "0.1142", "LastPrice": "4.41", "Yield": "2.59%", "ExDay": "5/6", "PayDay": "NA"}, {"Ticker": "abb", "Stock": "Abb Ltd", "Type": "A", "Dividend": "0.7972", "LastPrice": "20.28", "Yield": "3.93%", "ExDay": "5/6", "PayDay": "6/13"}, {"Ticker": "cqp", "Stock": "Cheniere Energy Partners LP Cheniere Energy Partn", "Type": "Q", "Dividend": "0.6", "LastPrice": "43.89", "Yield": "5.47%", "ExDay": "5/6", "PayDay": "5/15"}, {"Ticker": "nep", "Stock": "Nextera Energy Partners Lpunits Represent", "Type": "Q", "Dividend": "0.4825", "LastPrice": "45.22", "Yield": "4.27%", "ExDay": "5/6", "PayDay": "5/15"}, {"Ticker": "amtd", "Stock": "TD Ameritrade Holding Corporation", "Type": "Q", "Dividend": "0.3", "LastPrice": "53.43", "Yield": "2.25%", "ExDay": "5/6", "PayDay": "5/21"}, {"Ticker": "pmd", "Stock": "Psychemedics Corporation", "Type": "Q", "Dividend": "0.18", "LastPrice": "10.70", "Yield": "6.73%", "ExDay": "5/6", "PayDay": "5/17"}, {"Ticker": "et", "Stock": "Energy Transfer Lpunits", "Type": "Q", "Dividend": "0.305", "LastPrice": "14.91", "Yield": "8.18%", "ExDay": "5/6", "PayDay": "5/20"}, {"Ticker": "tmp", "Stock": "Tompkins Financial Corporation", "Type": "Q", "Dividend": "0.5", "LastPrice": "81.77", "Yield": "2.45%", "ExDay": "5/6", "PayDay": "5/15"}, {"Ticker": "dkl", "Stock": "Delek Logistics Partners L.P.UNITS Repres", "Type": "Q", "Dividend": "0.82", "LastPrice": "32.18", "Yield": "10.19%", "ExDay": "5/6", "PayDay": "5/14"}, {"Ticker": "-", "Stock": "\nAdvertising Opportunities on Dividend Channel"}, {"Ticker": "stl", "Stock": "Sterling Bancorp", "Type": "Q", "Dividend": "0.07", "LastPrice": "21.66", "Yield": "1.29%", "ExDay": "5/3", "PayDay": "5/20"}, {"Ticker": "lsbk", "Stock": "Lake Shore Bancorp Inc", "Type": "Q", "Dividend": "0.12", "LastPrice": "14.95", "Yield": "3.21%", "ExDay": "5/3", "PayDay": "5/20"}, {"Ticker": "amp", "Stock": "Ameriprise Financial Inc", "Type": "Q", "Dividend": "0.97", "LastPrice": "147.37", "Yield": "2.63%", "ExDay": "5/3", "PayDay": "5/17"}, {"Ticker": "fbiz", "Stock": "First Business Financial Services Inc", "Type": "Q", "Dividend": "0.15", "LastPrice": "23.13", "Yield": "2.59%", "ExDay": "5/3", "PayDay": "5/16"}, {"Ticker": "ab", "Stock": "Alliancebernstein Holding L.P. Units", "Type": "Q", "Dividend": "0.49", "LastPrice": "29.50", "Yield": "6.64%", "ExDay": "5/3", "PayDay": "5/16"}, {"Ticker": "alx", "Stock": "Alexanders Inc", "Type": "Q", "Dividend": "4.5", "LastPrice": "387.87", "Yield": "4.64%", "ExDay": "5/3", "PayDay": "5/17"}, {"Ticker": "asrv", "Stock": "Ameriserv Financial Inc", "Type": "Q", "Dividend": "0.025", "LastPrice": "4.20", "Yield": "2.38%", "ExDay": "5/3", "PayDay": "5/20"}, {"Ticker": "lyts", "Stock": "Lsi Industries Inc", "Type": "Q", "Dividend": "0.05", "LastPrice": "3.48", "Yield": "5.75%", "ExDay": "5/3", "PayDay": "5/14"}, {"Ticker": "pub", "Stock": "Peoples Utah Bancorp", "Type": "Q", "Dividend": "0.12", "LastPrice": "28.37", "Yield": "1.69%", "ExDay": "5/3", "PayDay": "5/13"}, {"Ticker": "dit", "Stock": "Amcon Distributing Company", "Type": "Q", "Dividend": "0.18", "LastPrice": "93.29", "Yield": "0.77%", "ExDay": "5/3", "PayDay": "5/28"}, {"Ticker": "ibtx", "Stock": "Independent Bank Group Inc", "Type": "Q", "Dividend": "0.25", "LastPrice": "56.18", "Yield": "1.78%", "ExDay": "5/3", "PayDay": "5/16"}, {"Ticker": "sjw", "Stock": "Sjw Group (de", "Type": "Q", "Dividend": "0.3", "LastPrice": "60.46", "Yield": "1.98%", "ExDay": "5/3", "PayDay": "6/3"}, {"Ticker": "matw", "Stock": "Matthews International Corporation - Class A Commo", "Type": "Q", "Dividend": "0.2", "LastPrice": "37.44", "Yield": "2.14%", "ExDay": "5/3", "PayDay": "5/20"}, {"Ticker": "uan", "Stock": "Cvr Partners Lpunits Representing Limited", "Type": "Q", "Dividend": "0.07", "LastPrice": "3.59", "Yield": "7.80%", "ExDay": "5/3", "PayDay": "5/13"}, {"Ticker": "laz", "Stock": "Lazard LTD. Lazard LTD. Class A", "Type": "Q", "Dividend": "0.47", "LastPrice": "38.18", "Yield": "4.92%", "ExDay": "5/3", "PayDay": "5/17"}, {"Ticker": "srce", "Stock": "1st Source Corporation", "Type": "Q", "Dividend": "0.27", "LastPrice": "47.51", "Yield": "2.27%", "ExDay": "5/3", "PayDay": "5/15"}, {"Ticker": "stnd", "Stock": "Standard Avb Financial Corp", "Type": "Q", "Dividend": "0.221", "LastPrice": "27.49", "Yield": "3.22%", "ExDay": "5/3", "PayDay": "5/20"}, {"Ticker": "glop", "Stock": "Gaslog Partners Lpunits Representing Limit", "Type": "Q", "Dividend": "0.55", "LastPrice": "21.10", "Yield": "10.43%", "ExDay": "5/3", "PayDay": "5/10"}, {"Ticker": "ocfc", "Stock": "Oceanfirst Financial Corp", "Type": "Q", "Dividend": "0.17", "LastPrice": "25.18", "Yield": "2.70%", "ExDay": "5/3", "PayDay": "5/17"}, {"Ticker": "bbdo", "Stock": "Banco Bradesco SA American Depositary Shares (each", "Type": "M", "Dividend": "0.0045", "LastPrice": "7.89", "Yield": "0.69%", "ExDay": "5/3", "PayDay": "6/10"}, {"Ticker": "wmk", "Stock": "Weis Markets Inc", "Type": "Q", "Dividend": "0.31", "LastPrice": "42.05", "Yield": "2.95%", "ExDay": "5/3", "PayDay": "5/20"}, {"Ticker": "sifi", "Stock": "SI Financial Group Inc", "Type": "Q", "Dividend": "0.06", "LastPrice": "14.30", "Yield": "1.68%", "ExDay": "5/3", "PayDay": "5/16"}, {"Ticker": "bgsf", "Stock": "BG Staffing Inc", "Type": "Q", "Dividend": "0.3", "LastPrice": "22.75", "Yield": "5.27%", "ExDay": "5/3", "PayDay": "5/13"}, {"Ticker": "fmx", "Stock": "Fomento Economico Mexicano S.A.B. DE C.V.", "Type": "S", "Dividend": "0.77", "LastPrice": "99.03", "Yield": "0.78%", "ExDay": "5/3", "PayDay": "5/17"}, {"Ticker": "kof", "Stock": "Coca Cola Femsa S.A.B. DE C.V. American Depositar", "Type": "S", "Dividend": "0.77", "LastPrice": "64.64", "Yield": "1.19%", "ExDay": "5/3", "PayDay": "5/17"}, {"Ticker": "mpv", "Stock": "Barings Participation Investors", "Type": "Q", "Dividend": "0.27", "LastPrice": "15.50", "Yield": "6.97%", "ExDay": "5/3", "PayDay": "5/17"}, {"Ticker": "ulh", "Stock": "Universal Logistics Holdings Inc", "Type": "Q", "Dividend": "0.105", "LastPrice": "23.26", "Yield": "1.81%", "ExDay": "5/3", "PayDay": "5/16"}, {"Ticker": "dlng.pra", "Stock": "Dynagas Lng Partners LP 9.00% Series A Cumulative", "Type": "Q", "Dividend": "0.5625", "LastPrice": "20.80", "Yield": "10.82%", "ExDay": "5/3", "PayDay": "5/13"}, {"Ticker": "hbcp", "Stock": "Home Bancorp Inc", "Type": "Q", "Dividend": "0.21", "LastPrice": "36.21", "Yield": "2.32%", "ExDay": "5/3", "PayDay": "5/17"}, {"Ticker": "ntb", "Stock": "Bank of N.T. Butterfield & Son Limited (the) Votin", "Type": "Q", "Dividend": "0.44", "LastPrice": "40.26", "Yield": "4.37%", "ExDay": "5/3", "PayDay": "5/17"}, {"Ticker": "cs", "Stock": "Credit Suisse Group American Depositary Shares", "Type": "A", "Dividend": "0.2641", "LastPrice": "13.24", "Yield": "1.99%", "ExDay": "5/3", "PayDay": "5/17"}, {"Ticker": "nblx", "Stock": "Noble Midstream Partners Lpunits Represent", "Type": "Q", "Dividend": "0.6132", "LastPrice": "33.90", "Yield": "7.24%", "ExDay": "5/3", "PayDay": "5/13"}, {"Ticker": "hcp", "Stock": "Hcp Inc", "Type": "Q", "Dividend": "0.37", "LastPrice": "30.54", "Yield": "4.85%", "ExDay": "5/3", "PayDay": "5/21"}, {"Ticker": "tts", "Stock": "Tile Shop Hldgs Inc", "Type": "Q", "Dividend": "0.05", "LastPrice": "4.72", "Yield": "4.24%", "ExDay": "5/3", "PayDay": "5/17"}, {"Ticker": "gne.pra", "Stock": "Genie Energy LTD. Series 2012 - A Preferred Stock", "Type": "Q", "Dividend": "0.1594", "LastPrice": "8.24", "Yield": "7.74%", "ExDay": "5/3", "PayDay": "5/15"}, {"Ticker": "cvi", "Stock": "Cvr Energy Inc", "Type": "Q", "Dividend": "0.75", "LastPrice": "44.63", "Yield": "6.72%", "ExDay": "5/3", "PayDay": "5/13"}, {"Ticker": "nsec", "Stock": "National Security Group Inc", "Type": "Q", "Dividend": "0.05", "LastPrice": "11.42", "Yield": "1.75%", "ExDay": "5/3", "PayDay": "5/31"}, {"Ticker": "nbl", "Stock": "Noble Energy Inc", "Type": "Q", "Dividend": "0.12", "LastPrice": "25.48", "Yield": "1.88%", "ExDay": "5/3", "PayDay": "5/20"}, {"Ticker": "c", "Stock": "Citigroup Inc", "Type": "Q", "Dividend": "0.45", "LastPrice": "70.36", "Yield": "2.56%", "ExDay": "5/3", "PayDay": "5/24"}, {"Ticker": "wabc", "Stock": "Westamerica Bancorporation", "Type": "Q", "Dividend": "0.41", "LastPrice": "63.98", "Yield": "2.56%", "ExDay": "5/3", "PayDay": "5/17"}, {"Ticker": "vno", "Stock": "Vornado Realty Trust", "Type": "Q", "Dividend": "0.66", "LastPrice": "67.96", "Yield": "3.88%", "ExDay": "5/3", "PayDay": "5/17"}, {"Ticker": "capl", "Stock": "Crossamerica Partners Lpunits Representing", "Type": "Q", "Dividend": "0.525", "LastPrice": "18.17", "Yield": "11.56%", "ExDay": "5/3", "PayDay": "5/13"}, {"Ticker": "ltxb", "Stock": "Legacytexas Financial Group Inc", "Type": "Q", "Dividend": "0.25", "LastPrice": "39.99", "Yield": "2.50%", "ExDay": "5/3", "PayDay": "5/20"}, {"Ticker": "shlx", "Stock": "Shell Midstream Partners L.P.UNITS Repres", "Type": "Q", "Dividend": "0.415", "LastPrice": "20.06", "Yield": "8.28%", "ExDay": "5/3", "PayDay": "5/15"}, {"Ticker": "mci", "Stock": "Barings Corporate Investors", "Type": "Q", "Dividend": "0.3", "LastPrice": "15.99", "Yield": "7.50%", "ExDay": "5/3", "PayDay": "5/17"}, {"Ticker": "pebo", "Stock": "Peoples Bancorp Inc", "Type": "Q", "Dividend": "0.34", "LastPrice": "32.56", "Yield": "4.18%", "ExDay": "5/3", "PayDay": "5/20"}, {"Ticker": "syf", "Stock": "Synchrony Financial", "Type": "Q", "Dividend": "0.21", "LastPrice": "34.15", "Yield": "2.46%", "ExDay": "5/3", "PayDay": "5/16"}, {"Ticker": "wbs", "Stock": "Webster Financial Corporation", "Type": "Q", "Dividend": "0.4", "LastPrice": "53.07", "Yield": "3.01%", "ExDay": "5/3", "PayDay": "5/20"}, {"Ticker": "cnxm", "Stock": "Cnx Midstream Partners Lpunits Representin", "Type": "Q", "Dividend": "0.3732", "LastPrice": "15.30", "Yield": "9.76%", "ExDay": "5/3", "PayDay": "5/14"}, {"Ticker": "ida", "Stock": "Idacorp Inc", "Type": "Q", "Dividend": "0.63", "LastPrice": "98.37", "Yield": "2.56%", "ExDay": "5/3", "PayDay": "5/30"}, {"Ticker": "bbd", "Stock": "Banco Bradesco SA American Depositary Shares", "Type": "M", "Dividend": "0.0050", "LastPrice": "8.98", "Yield": "0.66%", "ExDay": "5/3", "PayDay": "6/10"}, {"Ticker": "teo", "Stock": "Telecom Argentina SA", "Type": "A", "Dividend": "0.4504", "LastPrice": "13.43", "Yield": "3.35%", "ExDay": "5/3", "PayDay": "5/14"}, {"Ticker": "evtc", "Stock": "Evertec Inc", "Type": "Q", "Dividend": "0.05", "LastPrice": "29.71", "Yield": "0.67%", "ExDay": "5/3", "PayDay": "6/7"}, {"Ticker": "hafc", "Stock": "Hanmi Financial Corporation", "Type": "Q", "Dividend": "0.24", "LastPrice": "23.73", "Yield": "4.05%", "ExDay": "5/3", "PayDay": "5/31"}, {"Ticker": "ibcp", "Stock": "Independent Bank Corporation", "Type": "Q", "Dividend": "0.18", "LastPrice": "21.55", "Yield": "3.34%", "ExDay": "5/3", "PayDay": "5/15"}, {"Ticker": "txn", "Stock": "Texas Instruments Incorporated", "Type": "Q", "Dividend": "0.77", "LastPrice": "117.46", "Yield": "2.62%", "ExDay": "5/3", "PayDay": "5/20"}, {"Ticker": "cwt", "Stock": "California Water Service Group", "Type": "Q", "Dividend": "0.1975", "LastPrice": "49.72", "Yield": "1.59%", "ExDay": "5/3", "PayDay": "5/17"}, {"Ticker": "krp", "Stock": "Kimbell Royalty Partnersunits Representing", "Type": "Q", "Dividend": "0.37", "LastPrice": "16.61", "Yield": "8.91%", "ExDay": "5/3", "PayDay": "5/13"}, {"Ticker": "oak", "Stock": "Oaktree Capital Group Llc Class A Units Represent", "Type": "Q", "Dividend": "1.05", "LastPrice": "50.31", "Yield": "8.35%", "ExDay": "5/3", "PayDay": "5/10"}, {"Ticker": "royt", "Stock": "Pacific Coast Oil Trust Units of Beneficial Intere", "Type": "M", "Dividend": "0.0279", "LastPrice": "2.26", "Yield": "14.82%", "ExDay": "5/3", "PayDay": "5/20"}, {"Ticker": "gmlp", "Stock": "Golar Lng Partners Lpunits Representing", "Type": "Q", "Dividend": "0.4042", "LastPrice": "12.90", "Yield": "12.53%", "ExDay": "5/6", "PayDay": "5/14"}, {"Ticker": "cig", "Stock": "Comp EN DE MN Cemig Ads American Depositary Shares", "Type": "A", "Dividend": "0.1142", "LastPrice": "3.68", "Yield": "3.10%", "ExDay": "5/6", "PayDay": "NA"}, {"Ticker": "safm", "Stock": "Sanderson Farms Inc", "Type": "Q", "Dividend": "0.32", "LastPrice": "147.94", "Yield": "0.87%", "ExDay": "5/6", "PayDay": "5/21"}, {"Ticker": "sun", "Stock": "Sunoco Lpunits Representing Limited Partne", "Type": "Q", "Dividend": "0.8255", "LastPrice": "31.18", "Yield": "10.59%", "ExDay": "5/6", "PayDay": "5/15"}, {"Ticker": "fe", "Stock": "Firstenergy Corp", "Type": "Q", "Dividend": "0.38", "LastPrice": "41.97", "Yield": "3.62%", "ExDay": "5/6", "PayDay": "6/1"}, {"Ticker": "tgp", "Stock": "Teekay Lng Partners L.P.", "Type": "Q", "Dividend": "0.19", "LastPrice": "14.89", "Yield": "5.10%", "ExDay": "5/6", "PayDay": "5/15"}, {"Ticker": "ccr", "Stock": "Consol Coal Resources Lpunits Representing", "Type": "Q", "Dividend": "0.5125", "LastPrice": "17.72", "Yield": "11.57%", "ExDay": "5/6", "PayDay": "5/15"}, {"Ticker": "ngl", "Stock": "Ngl Energy Partners Lpunits Representing L", "Type": "Q", "Dividend": "0.39", "LastPrice": "13.52", "Yield": "11.54%", "ExDay": "5/6", "PayDay": "5/15"}, {"Ticker": "usdp", "Stock": "Usd Partners Lpunits Representing Limited", "Type": "Q", "Dividend": "0.3625", "LastPrice": "11.14", "Yield": "13.02%", "ExDay": "5/6", "PayDay": "5/15"}, {"Ticker": "sph", "Stock": "Suburban Propane Partners L.P.", "Type": "Q", "Dividend": "0.6", "LastPrice": "23.48", "Yield": "10.22%", "ExDay": "5/6", "PayDay": "5/14"}, {"Ticker": "intc", "Stock": "Intel Corporation", "Type": "Q", "Dividend": "0.315", "LastPrice": "50.55", "Yield": "2.49%", "ExDay": "5/6", "PayDay": "6/1"}, {"Ticker": "cig.c", "Stock": "Comp EN DE MN Cemig Ads American Depositary Receip", "Type": "A", "Dividend": "0.1142", "LastPrice": "4.41", "Yield": "2.59%", "ExDay": "5/6", "PayDay": "NA"}, {"Ticker": "abb", "Stock": "Abb Ltd", "Type": "A", "Dividend": "0.7972", "LastPrice": "20.28", "Yield": "3.93%", "ExDay": "5/6", "PayDay": "6/13"}, {"Ticker": "cqp", "Stock": "Cheniere Energy Partners LP Cheniere Energy Partn", "Type": "Q", "Dividend": "0.6", "LastPrice": "43.89", "Yield": "5.47%", "ExDay": "5/6", "PayDay": "5/15"}, {"Ticker": "nep", "Stock": "Nextera Energy Partners Lpunits Represent", "Type": "Q", "Dividend": "0.4825", "LastPrice": "45.22", "Yield": "4.27%", "ExDay": "5/6", "PayDay": "5/15"}, {"Ticker": "amtd", "Stock": "TD Ameritrade Holding Corporation", "Type": "Q", "Dividend": "0.3", "LastPrice": "53.43", "Yield": "2.25%", "ExDay": "5/6", "PayDay": "5/21"}, {"Ticker": "pmd", "Stock": "Psychemedics Corporation", "Type": "Q", "Dividend": "0.18", "LastPrice": "10.70", "Yield": "6.73%", "ExDay": "5/6", "PayDay": "5/17"}, {"Ticker": "et", "Stock": "Energy Transfer Lpunits", "Type": "Q", "Dividend": "0.305", "LastPrice": "14.91", "Yield": "8.18%", "ExDay": "5/6", "PayDay": "5/20"}, {"Ticker": "tmp", "Stock": "Tompkins Financial Corporation", "Type": "Q", "Dividend": "0.5", "LastPrice": "81.77", "Yield": "2.45%", "ExDay": "5/6", "PayDay": "5/15"}, {"Ticker": "dkl", "Stock": "Delek Logistics Partners L.P.UNITS Repres", "Type": "Q", "Dividend": "0.82", "LastPrice": "32.18", "Yield": "10.19%", "ExDay": "5/6", "PayDay": "5/14"}]