[{"ticker": "DWDP", "shares": 15, "price": 30.52, "value": 457.8, "target_price": 38, "?column?": 156.0, "exp_value": 1170, "target": 78, "to_char": "06/27/2019", "DivHistory": {}}, {"ticker": "ERF", "shares": 50, "price": 7.26, "value": 363.0, "target_price": 10, "?column?": 93.0, "exp_value": 700, "target": 14, "to_char": "07/02/2019", "DivHistory": {}}, {"ticker": "OLN", "shares": 18, "price": 21.38, "value": 384.84, "target_price": 25, "?column?": 36.0, "exp_value": 522, "target": 29, "to_char": "06/28/2019", "DivHistory": {}}, {"ticker": "STMP", "shares": 4, "price": 45.63, "value": 182.52, "target_price": 110, "?column?": 29.0, "exp_value": 236, "target": 59, "to_char": "06/04/2019", "DivHistory": {}}, {"ticker": "PXD", "shares": 1, "price": 145.55, "value": 145.55, "target_price": 241, "?column?": 28.0, "exp_value": 186, "target": 186, "to_char": "06/03/2019", "DivHistory": {}}, {"ticker": "PATK", "shares": 15, "price": 48.05, "value": 720.75, "target_price": 55, "?column?": 27.0, "exp_value": 915, "target": 61, "to_char": "06/12/2019", "DivHistory": {}}, {"ticker": "WDC", "shares": 3, "price": 47.94, "value": 143.82, "target_price": 72, "?column?": 23.0, "exp_value": 177, "target": 59, "to_char": "06/13/2019", "DivHistory": {}}, {"ticker": "LNC", "shares": 5, "price": 65.71, "value": 328.55, "target_price": 78, "?column?": 16.0, "exp_value": 380, "target": 76, "to_char": "06/29/2019", "DivHistory": {}}, {"ticker": "FMC", "shares": 3, "price": 84.79, "value": 254.37, "target_price": 104, "?column?": 10.0, "exp_value": 279, "target": 93, "to_char": "06/07/2019", "DivHistory": {}}, {"ticker": "CELG", "shares": 3, "price": 94.36, "value": 283.08, "target_price": 106, "?column?": 0.0, "exp_value": 282, "target": 94, "to_char": "07/01/2019", "DivHistory": {}}]